Workbook

Sheet Настройки
A1: Параметр | B1: Значение | C1: Пояснение
A2: Адрес лендинга | B2: https://renal-auto.ru/port | C2: Жёлтые ячейки можно менять. Ссылки на листе «Объявления» собираются из этого адреса формулой. Запускать рекламу — после переезда на renal-auto.ru (docs/MOVE_SERVER.md).
A3: UTM-метки | B3: utm_source=yandex&utm_medium=cpc&utm_campaign={campaign_id}&utm_content={ad_id}&utm_term={keyword} | C3: {…} — динамические параметры Директа, подставятся сами.
A4: Тип кампании | B4: Единая перфоманс-кампания | C4: Для старта — только поиск: в «Местах показа» отключите сети, пока не наберётся статистика.
A5: Регион показа | B5: Россия | C5: Допущение: возим по всей России. Если хотите начать с Дальнего Востока и Сибири — сузьте здесь.
A6: Стратегия на первые 2 недели | B6: Максимум кликов, недельный бюджет | C6: После 10+ заявок в неделю — переключить на «Максимум конверсий» по цели «lead».
A7: Недельный бюджет теста, ₽ | B7: 15000 | C7: Допущение для теста, не рекомендация по итоговому бюджету — поменяйте под себя.
A8: Счётчик Метрики | B8: 113699503 | C8: Уже стоит на лендинге.
A9: Цель для оптимизации | B9: lead — отправленная заявка | C9: Другие цели лендинга: car_click, car_trip, form_open, max, reviews_2gis — для анализа, не для оптимизации.
A10: Расписание | B10: Ежедневно 8:00–23:00 | C10: По времени региона показа.
A11: Минус-слова | B11: лист «Минус-слова» | C11: Добавить на уровень кампании целиком.
A12: Быстрые ссылки и уточнения | B12: лист «Быстрые ссылки» | C12: Один набор на все группы.
A13: Проверка длины | B13: столбцы «Длина» на листе «Объявления» | C13: Красная заливка — текст длиннее лимита Директа (заголовок 1 — 56, заголовок 2 — 30, текст — 81, отображаемая ссылка — 20).

Sheet Объявления
A1: Кампания | B1: Группа | C1: Вариант | D1: Заголовок 1 | E1: Длина | F1: Заголовок 2 | G1: Длина | H1: Текст | I1: Длина | J1: Отображаемая ссылка | K1: Длина | L1: ?model= | M1: Ссылка (формула)
A2: Корея — модели | B2: Kia K5 | C2: А | D2: Kia K5 из Кореи — подберём оптимальный вариант | E2: =LEN(D2) | F2: Комиссия до 50 000 ₽ | G2: =LEN(F2) | H2: Сравним объявления, проверим историю и проходимость в РФ. Цены онлайн в рублях. | I2: =LEN(H2) | J2: Kia-K5 | K2: =LEN(J2) | L2: K5 | M2: =Настройки!$B$2&IF(L2="","?","?model="&SUBSTITUTE(L2," ","+")&"&")&Настройки!$B$3
A3: Корея — модели | B3: Kia K5 | C3: Б | D3: Kia K5 из Кореи: проверим историю до покупки | E3: =LEN(D3) | F3: Агентский договор | G3: =LEN(F3) | H3: Реальные объявления с ценой в рублях. Посмотрите, как машина поедет к вам. | I3: =LEN(H3) | J3: Kia-K5 | K3: =LEN(J3) | L3: K5 | M3: =Настройки!$B$2&IF(L3="","?","?model="&SUBSTITUTE(L3," ","+")&"&")&Настройки!$B$3
A4: Корея — модели | B4: Kia Sportage | C4: А | D4: Kia Sportage из Кореи — подберём оптимальный вариант | E4: =LEN(D4) | F4: Комиссия до 50 000 ₽ | G4: =LEN(F4) | H4: Сравним объявления, проверим историю и проходимость в РФ. Цены онлайн в рублях. | I4: =LEN(H4) | J4: Kia-Sportage | K4: =LEN(J4) | L4: Sportage | M4: =Настройки!$B$2&IF(L4="","?","?model="&SUBSTITUTE(L4," ","+")&"&")&Настройки!$B$3
A5: Корея — модели | B5: Kia Sportage | C5: Б | D5: Kia Sportage из Кореи: проверим историю до покупки | E5: =LEN(D5) | F5: Агентский договор | G5: =LEN(F5) | H5: Реальные объявления с ценой в рублях. Посмотрите, как машина поедет к вам. | I5: =LEN(H5) | J5: Kia-Sportage | K5: =LEN(J5) | L5: Sportage | M5: =Настройки!$B$2&IF(L5="","?","?model="&SUBSTITUTE(L5," ","+")&"&")&Настройки!$B$3
A6: Корея — модели | B6: Kia Sorento | C6: А | D6: Kia Sorento из Кореи — подберём оптимальный вариант | E6: =LEN(D6) | F6: Комиссия до 50 000 ₽ | G6: =LEN(F6) | H6: Сравним объявления, проверим историю и проходимость в РФ. Цены онлайн в рублях. | I6: =LEN(H6) | J6: Kia-Sorento | K6: =LEN(J6) | L6: Sorento | M6: =Настройки!$B$2&IF(L6="","?","?model="&SUBSTITUTE(L6," ","+")&"&")&Настройки!$B$3
A7: Корея — модели | B7: Kia Sorento | C7: Б | D7: Kia Sorento из Кореи: проверим историю до покупки | E7: =LEN(D7) | F7: Агентский договор | G7: =LEN(F7) | H7: Реальные объявления с ценой в рублях. Посмотрите, как машина поедет к вам. | I7: =LEN(H7) | J7: Kia-Sorento | K7: =LEN(J7) | L7: Sorento | M7: =Настройки!$B$2&IF(L7="","?","?model="&SUBSTITUTE(L7," ","+")&"&")&Настройки!$B$3
A8: Корея — модели | B8: Kia Seltos | C8: А | D8: Kia Seltos из Кореи — подберём оптимальный вариант | E8: =LEN(D8) | F8: Комиссия до 50 000 ₽ | G8: =LEN(F8) | H8: Сравним объявления, проверим историю и проходимость в РФ. Цены онлайн в рублях. | I8: =LEN(H8) | J8: Kia-Seltos | K8: =LEN(J8) | L8: Seltos | M8: =Настройки!$B$2&IF(L8="","?","?model="&SUBSTITUTE(L8," ","+")&"&")&Настройки!$B$3
A9: Корея — модели | B9: Kia Seltos | C9: Б | D9: Kia Seltos из Кореи: проверим историю до покупки | E9: =LEN(D9) | F9: Агентский договор | G9: =LEN(F9) | H9: Реальные объявления с ценой в рублях. Посмотрите, как машина поедет к вам. | I9: =LEN(H9) | J9: Kia-Seltos | K9: =LEN(J9) | L9: Seltos | M9: =Настройки!$B$2&IF(L9="","?","?model="&SUBSTITUTE(L9," ","+")&"&")&Настройки!$B$3
A10: Корея — модели | B10: Kia Carnival | C10: А | D10: Kia Carnival из Кореи — подберём оптимальный вариант | E10: =LEN(D10) | F10: Комиссия до 50 000 ₽ | G10: =LEN(F10) | H10: Сравним объявления, проверим историю и проходимость в РФ. Цены онлайн в рублях. | I10: =LEN(H10) | J10: Kia-Carnival | K10: =LEN(J10) | L10: Carnival | M10: =Настройки!$B$2&IF(L10="","?","?model="&SUBSTITUTE(L10," ","+")&"&")&Настройки!$B$3
A11: Корея — модели | B11: Kia Carnival | C11: Б | D11: Kia Carnival из Кореи: проверим историю до покупки | E11: =LEN(D11) | F11: Агентский договор | G11: =LEN(F11) | H11: Реальные объявления с ценой в рублях. Посмотрите, как машина поедет к вам. | I11: =LEN(H11) | J11: Kia-Carnival | K11: =LEN(J11) | L11: Carnival | M11: =Настройки!$B$2&IF(L11="","?","?model="&SUBSTITUTE(L11," ","+")&"&")&Настройки!$B$3
A12: Корея — модели | B12: Kia Ray | C12: А | D12: Kia Ray из Кореи — подберём оптимальный вариант | E12: =LEN(D12) | F12: Комиссия до 50 000 ₽ | G12: =LEN(F12) | H12: Сравним объявления, проверим историю и проходимость в РФ. Цены онлайн в рублях. | I12: =LEN(H12) | J12: Kia-Ray | K12: =LEN(J12) | L12: Ray | M12: =Настройки!$B$2&IF(L12="","?","?model="&SUBSTITUTE(L12," ","+")&"&")&Настройки!$B$3
A13: Корея — модели | B13: Kia Ray | C13: Б | D13: Kia Ray из Кореи: проверим историю до покупки | E13: =LEN(D13) | F13: Агентский договор | G13: =LEN(F13) | H13: Реальные объявления с ценой в рублях. Посмотрите, как машина поедет к вам. | I13: =LEN(H13) | J13: Kia-Ray | K13: =LEN(J13) | L13: Ray | M13: =Настройки!$B$2&IF(L13="","?","?model="&SUBSTITUTE(L13," ","+")&"&")&Настройки!$B$3
... A39: Китай — модели | B39: Changan UNI-K | C39: Б | D39: Changan UNI-K из Китая: проверим историю до покупки | E39: =LEN(D39) | F39: Агентский договор | G39: =LEN(F39) | H39: Реальные объявления с ценой в рублях. Посмотрите, как машина поедет к вам. | I39: =LEN(H39) | J39: Changan-UNI-K | K39: =LEN(J39) | L39: UNI-K | M39: =Настройки!$B$2&IF(L39="","?","?model="&SUBSTITUTE(L39," ","+")&"&")&Настройки!$B$3
A40: Общие | B40: Авто из Кореи | C40: А | D40: Авто из Кореи — подберём оптимальный вариант | E40: =LEN(D40) | F40: Комиссия до 50 000 ₽ | G40: =LEN(F40) | H40: Сравним объявления, проверим историю и проходимость в РФ. Цены онлайн в рублях. | I40: =LEN(H40) | J40: Авто-из-Кореи | K40: =LEN(J40) | M40: =Настройки!$B$2&IF(L40="","?","?model="&SUBSTITUTE(L40," ","+")&"&")&Настройки!$B$3
A41: Общие | B41: Авто из Кореи | C41: Б | D41: Авто из Кореи: проверим историю до покупки | E41: =LEN(D41) | F41: Агентский договор | G41: =LEN(F41) | H41: Реальные объявления с ценой в рублях. Посмотрите, как машина поедет к вам. | I41: =LEN(H41) | J41: Авто-из-Кореи | K41: =LEN(J41) | M41: =Настройки!$B$2&IF(L41="","?","?model="&SUBSTITUTE(L41," ","+")&"&")&Настройки!$B$3
A42: Общие | B42: Авто из Китая | C42: А | D42: Авто из Китая — подберём оптимальный вариант | E42: =LEN(D42) | F42: Комиссия до 50 000 ₽ | G42: =LEN(F42) | H42: Сравним объявления, проверим историю и проходимость в РФ. Цены онлайн в рублях. | I42: =LEN(H42) | J42: Авто-из-Китая | K42: =LEN(J42) | M42: =Настройки!$B$2&IF(L42="","?","?model="&SUBSTITUTE(L42," ","+")&"&")&Настройки!$B$3
A43: Общие | B43: Авто из Китая | C43: Б | D43: Авто из Китая: проверим историю до покупки | E43: =LEN(D43) | F43: Агентский договор | G43: =LEN(F43) | H43: Реальные объявления с ценой в рублях. Посмотрите, как машина поедет к вам. | I43: =LEN(H43) | J43: Авто-из-Китая | K43: =LEN(J43) | M43: =Настройки!$B$2&IF(L43="","?","?model="&SUBSTITUTE(L43," ","+")&"&")&Настройки!$B$3
A44: Общие | B44: Подбор авто из Кореи и Китая | C44: А | D44: Авто из Кореи и Китая — подберём оптимальный вариант | E44: =LEN(D44) | F44: Комиссия до 50 000 ₽ | G44: =LEN(F44) | H44: Сравним объявления, проверим историю и проходимость в РФ. Цены онлайн в рублях. | I44: =LEN(H44) | J44: Подбор-авто | K44: =LEN(J44) | M44: =Настройки!$B$2&IF(L44="","?","?model="&SUBSTITUTE(L44," ","+")&"&")&Настройки!$B$3
A45: Общие | B45: Подбор авто из Кореи и Китая | C45: Б | D45: Авто из Кореи и Китая: проверим историю до покупки | E45: =LEN(D45) | F45: Агентский договор | G45: =LEN(F45) | H45: Реальные объявления с ценой в рублях. Посмотрите, как машина поедет к вам. | I45: =LEN(H45) | J45: Подбор-авто | K45: =LEN(J45) | M45: =Настройки!$B$2&IF(L45="","?","?model="&SUBSTITUTE(L45," ","+")&"&")&Настройки!$B$3

Sheet Фразы
A1: Кампания | B1: Группа | C1: Ключевая фраза
A2: Корея — модели | B2: Kia K5 | C2: киа к5 из кореи
A3: Корея — модели | B3: Kia K5 | C3: купить киа к5 из кореи
A4: Корея — модели | B4: Kia K5 | C4: киа к5 из кореи цена
A5: Корея — модели | B5: Kia K5 | C5: заказать киа к5 из кореи
A6: Корея — модели | B6: Kia K5 | C6: пригнать киа к5 из кореи
A7: Корея — модели | B7: Kia K5 | C7: kia k5 из кореи
A8: Корея — модели | B8: Kia K5 | C8: купить kia k5 из кореи
A9: Корея — модели | B9: Kia K5 | C9: kia k5 из кореи цена
A10: Корея — модели | B10: Kia K5 | C10: заказать kia k5 из кореи
A11: Корея — модели | B11: Kia K5 | C11: пригнать kia k5 из кореи
A12: Корея — модели | B12: Kia K5 | C12: киа оптима к5 из кореи
... A224: Общие | B224: Подбор авто из Кореи и Китая | C224: калькулятор растаможки авто из китая
A226: Фразы с «под ключ» оставлены: так ищут. В текстах объявлений «под ключ» не используем — цена ориентировочная.

Sheet Минус-слова
A1: Минус-слово | B1: Зачем
A2: запчасти | B2: не продаём запчасти
A3: разборка
A4: разбор
A5: ремонт
A6: сервис
A7: шины
A8: диски
A9: тюнинг
A10: аренда | B10: не сдаём машины
A11: прокат
A12: такси
A13: лизинг | B13: не оформляем лизинг — уберите, если появится
A14: вакансии | B14: не ищем сотрудников
A15: работа
A16: водитель
A17: игрушка | B17: модели и игры
A18: масштабная
A19: гта
A20: игра
A21: скачать
A22: мод
A23: раскраска
A24: обзор | B24: ищут информацию, а не покупку
A25: тест-драйв
A26: характеристики
A27: расход
A28: габариты
A29: японии | B29: не возим из Японии
A30: сша | B30: не возим из США
A31: европы
A32: германии
A33: оаэ
A34: грузии
A35: авито | B35: ищут на площадках, не у нас
A36: дром
A37: автору

Sheet Быстрые ссылки
A1: Тип | B1: Заголовок | C1: Длина | D1: Описание | E1: Длина | F1: Якорь на странице | G1: Ссылка (формула)
A2: Быстрая ссылка | B2: Объявления онлайн | C2: =LEN(B2) | D2: Свежие машины из Кореи и Китая с ценой в рублях | E2: =LEN(D2) | F2: #terminal | G2: =Настройки!$B$2&"?"&Настройки!$B$3&F2
A3: Быстрая ссылка | B3: Как машина поедет к вам | C3: =LEN(B3) | D3: Покажем путь от площадки до вашего города | E3: =LEN(D3) | F3: #route | G3: =Настройки!$B$2&"?"&Настройки!$B$3&F3
A4: Быстрая ссылка | B4: Отзывы и выдачи | C4: =LEN(B4) | D4: Видео с выдач и отзывы клиентов в 2ГИС | E4: =LEN(D4) | F4: #vydachi | G4: =Настройки!$B$2&"?"&Настройки!$B$3&F4
A5: Быстрая ссылка | B5: Проверьте нас | C5: =LEN(B5) | D5: Юрлицо, офис во Владивостоке, договор | E5: =LEN(D5) | F5: #vydachi | G5: =Настройки!$B$2&"?"&Настройки!$B$3&F5
A6: Уточнение | B6: Агентский договор | C6: =LEN(B6)
A7: Уточнение | B7: Комиссия до 50 000 ₽ | C7: =LEN(B7)
A8: Уточнение | B8: Проверка истории и VIN | C8: =LEN(B8)
A9: Уточнение | B9: Видео с площадки | C9: =LEN(B9)
